tinyssg/__init__.py
tinyssg/__main__.py
tinyssg-1.3.0.dist-info/METADATA
tinyssg-1.3.0.dist-info/WHEEL
tinyssg-1.3.0.dist-info/top_level.txt
tinyssg-1.3.0.dist-info/RECORD
